lib_rr/Funciones.py
lib_rr/__init__.py
lib_rr/algoritmo_genetico.py
lib_rr-0.2.9.dist-info/METADATA
lib_rr-0.2.9.dist-info/WHEEL
lib_rr-0.2.9.dist-info/top_level.txt
lib_rr-0.2.9.dist-info/RECORD
