Metadata-Version: 2.1
Name: lib-rr
Version: 0.2.9
Summary: A test library
Home-page: https://github.com/JorgeRodriguez9/lib_rr
Author: Jorge Rodriguez
Author-email: jarodriguezcastano@ucundinamarca.edu.co
License: UNKNOWN
Platform: UNKNOWN
Classifier: Programming Language :: Python :: 3
Classifier: License :: OSI Approved :: MIT License
Classifier: Operating System :: OS Independent
Requires-Python: >=3.6
Requires-Dist: numpy
